secondbrain/__init__.py
secondbrain/address/__init__.py
secondbrain/address/address.py
secondbrain/address/workspace.py
secondbrain/ai/__init__.py
secondbrain/ai/llm/__init__.py
secondbrain/ai/llm/chat.py
secondbrain/ai/llm/text_to_image_prompt.py
secondbrain/api/__init__.py
secondbrain/api/lib/__init__.py
secondbrain/api/lib/tab.py
secondbrain/api/lib/view.py
secondbrain/api/lib/web.py
secondbrain/api/lib/window.py
secondbrain/bot/__init__.py
secondbrain/bot/chat.py
secondbrain/bot/chat_base.py
secondbrain/bot/history.py
secondbrain/bot/interrupt.py
secondbrain/bot/lib.py
secondbrain/bot/message.py
secondbrain/bot/prompt.jinja
secondbrain/bot/prompt.py
secondbrain/reference/__init__.py
secondbrain/reference/bot.py
secondbrain/reference/mcp.py
secondbrain/reference/tool.py
secondbrain/reference/workflow.py
secondbrain/reference/lib/__init__.py
secondbrain/reference/lib/call_func.py
secondbrain/reference/lib/change_directory.py
secondbrain/tool/__init__.py
secondbrain/tool/tool_decorator.py
secondbrain/ui/__init__.py
secondbrain/ui/base.py
secondbrain/ui/color.py
secondbrain/ui/typ.py
secondbrain/ui/ui_def.py
secondbrain/utils/__init__.py
secondbrain/utils/arg.py
secondbrain/utils/env.py
secondbrain/utils/json.py
secondbrain/utils/process.py
secondbrain/utils/socket.py
secondbrain/utils/text_or_file.py
secondbrain/utils/web.py
secondbrain-0.0.79.dist-info/LICENSE
secondbrain-0.0.79.dist-info/METADATA
secondbrain-0.0.79.dist-info/WHEEL
secondbrain-0.0.79.dist-info/top_level.txt
secondbrain-0.0.79.dist-info/RECORD
