Metadata-Version: 2.2
Name: secondbrain
Version: 0.0.79
Summary: Package for secondbrain only!
Author: Jie Xiong
Author-email: 363692146@qq.com
Classifier: Programming Language :: Python :: 3
Classifier: License :: OSI Approved :: MIT License
Classifier: Operating System :: OS Independent
Requires-Python: >=3.6
License-File: LICENSE
Dynamic: author
Dynamic: author-email
Dynamic: classifier
Dynamic: description
Dynamic: description-content-type
Dynamic: requires-python
Dynamic: summary
